{"lthlan54@gmail.com":{"email":"lthlan54@gmail.com","password":"202cb962ac59075b964b07152d234b70","fullName":"HaiLan","secret":"7FH6NYV57LQYOAMN","setting":"on"},"abc@gmail.com":{"email":"abc@gmail.com","password":"202cb962ac59075b964b07152d234b70","fullName":"Abc","secret":"7AKHQNURICJ6SGML","setting":"init"},"minhhuy97.ptit@gmail.com":{"email":"minhhuy97.ptit@gmail.com","password":"3997b0042e8cb97e9401952a079e3f7c","fullName":"Nguy\u1ec5n H\u00e0 Minh Huy","secret":"QN3U5MMBVXFNP3E6","setting":"on"}}